mongo_migrate/__init__.py
mongo_migrate/base_migrate.py
mongo_migrate/exceptions.py
mongo_migrate/migration_cli.py
mongo_migrate/migration_manager.py
mongo_migrate2-0.1.2.dist-info/licenses/LICENSE
mongo_migrate2-0.1.2.dist-info/METADATA
mongo_migrate2-0.1.2.dist-info/WHEEL
mongo_migrate2-0.1.2.dist-info/entry_points.txt
mongo_migrate2-0.1.2.dist-info/top_level.txt
mongo_migrate2-0.1.2.dist-info/RECORD
