Metadata-Version: 2.4
Name: mongo_migrate2
Version: 0.1.2
Summary: Migrate mongodb seamlessly with python and mongo-migrate. Supports migration creation, upgrade, and downgrade
Author-email: Martinbndr <55140357+martinbndr@users.noreply.github.com>
License: MIT License
Project-URL: Repository, https://github.com/martinbndr/mongo-migrate
Project-URL: Bug Tracker, https://github.com/martinbndr/mongo-migrate/issues
Project-URL: Blog, https://rahulgeorge.hashnode.dev/migrate-mongodb-data-seamlessly-with-mongo-migrate-and-python
Keywords: mongodb,migration,mongodb migration,database,automation
Classifier: License :: OSI Approved :: MIT License
Classifier: Intended Audience :: Developers
Classifier: Operating System :: OS Independent
Classifier: Programming Language :: Python
Classifier: Programming Language :: Python :: 3
Classifier: Programming Language :: Python :: 3.8
Classifier: Programming Language :: Python :: 3.9
Classifier: Programming Language :: Python :: 3.10
Classifier: Programming Language :: Python :: 3.11
Classifier: Topic :: Software Development :: Libraries :: Python Modules
Classifier: Topic :: Database
Requires-Python: >=3.7
License-File: LICENSE
Requires-Dist: pymongo
Requires-Dist: tomli; python_version < "3.11"
Dynamic: license-file
